LICENSE
README.md
setup.py
denilson_fib_py.egg-info/PKG-INFO
denilson_fib_py.egg-info/SOURCES.txt
denilson_fib_py.egg-info/dependency_links.txt
denilson_fib_py.egg-info/entry_points.txt
denilson_fib_py.egg-info/requires.txt
denilson_fib_py.egg-info/top_level.txt
fib_py/__init__.py
fib_py/version.py
fib_py/cmd/__init__.py
fib_py/cmd/fib_numb.py
fib_py/fib_calcs/__init__.py
fib_py/fib_calcs/fib_number.py
fib_py/fib_calcs/fib_numbers.py
tests/fib_py/__init__.py
tests/fib_py/fib_calcs/__init__.py
tests/fib_py/fib_calcs/test_fib_number.py
tests/fib_py/fib_calcs/test_fib_numbers.py