Metadata-Version: 2.1
Name: denilson-fib-py
Version: 0.0.3
Summary: Recursive fibonacci
Home-page: https://github.com/denilson020898/test-fib-py
Author: Denilson
Author-email: denilson020898@gmail.com
License: UNKNOWN
Platform: UNKNOWN
Classifier: Development Status :: 4 - Beta
Classifier: Programming Language :: Python :: 3
Classifier: Operating System :: OS Independent
Requires-Python: >=3
Provides-Extra: server
License-File: LICENSE
